TesAPI/Client.py
TesAPI/Exceptions.py
TesAPI/__init__.py
TesAPI/setup.py
TesAPI-2.1.dist-info/METADATA
TesAPI-2.1.dist-info/WHEEL
TesAPI-2.1.dist-info/top_level.txt
TesAPI-2.1.dist-info/RECORD
