Metadata-Version: 2.1
Name: TesAPI
Version: 2.1
Summary: Client For TesAPI
Author: Tes_Npe
Author-email: antoshaspr@vk.com
Classifier: Programming Language :: Python :: 3
Classifier: License :: OSI Approved :: MIT License
Classifier: Operating System :: OS Independent
Requires-Python: >=3.12.4
Requires-Dist: requests
Requires-Dist: TesRSA
